cardsharp/__init__.py
cardsharp/blackjack/__init__.py
cardsharp/blackjack/action.py
cardsharp/blackjack/actor.py
cardsharp/blackjack/bankroll.py
cardsharp/blackjack/basic_strategy.csv
cardsharp/blackjack/blackjack.py
cardsharp/blackjack/casino.py
cardsharp/blackjack/environment.py
cardsharp/blackjack/execution_variance.py
cardsharp/blackjack/hand.py
cardsharp/blackjack/realistic_strategy.py
cardsharp/blackjack/rules.py
cardsharp/blackjack/state.py
cardsharp/blackjack/state_events.py
cardsharp/blackjack/stats.py
cardsharp/blackjack/strategy.py
cardsharp/common/__init__.py
cardsharp/common/actor.py
cardsharp/common/card.py
cardsharp/common/deck.py
cardsharp/common/hand.py
cardsharp/common/io_interface.py
cardsharp/common/shoe.py
cardsharp/common/state.py
cardsharp/common/util.py
cardsharp/high_card/high_card.py
cardsharp/roulette/__init__.py
cardsharp/roulette/actor.py
cardsharp/tools/__init__.py
cardsharp/tools/verify_rules.py
cardsharp/ui/blackjack_ui.py
cardsharp/verification/__init__.py
cardsharp/verification/events.py
cardsharp/verification/main.py
cardsharp/verification/playback.py
cardsharp/verification/schema.py
cardsharp/verification/statistics.py
cardsharp/verification/storage.py
cardsharp/verification/verifier.py
cardsharp/war/war.py
cardsharp-0.5.0.dist-info/LICENSE
cardsharp-0.5.0.dist-info/METADATA
cardsharp-0.5.0.dist-info/WHEEL
cardsharp-0.5.0.dist-info/RECORD
