Metadata-Version: 2.3
Name: cardsharp
Version: 0.5.0
Summary: Card Playing Simulator focused on Blackjack
License: MIT
Author: Matt Michie
Author-email: mmichie@gmail.com
Requires-Python: >=3.12,<4.0
Classifier: Development Status :: 3 - Alpha
Classifier: Intended Audience :: Developers
Classifier: License :: OSI Approved :: MIT License
Classifier: Programming Language :: Python :: 3
Classifier: Programming Language :: Python :: 3.12
Classifier: Programming Language :: Python :: 3.13
Classifier: Topic :: Games/Entertainment :: Board Games
Requires-Dist: aiofiles (>=24.0.0)
Requires-Dist: asyncio (>=3.4.3,<4.0.0)
Requires-Dist: matplotlib (>=3.9.2,<4.0.0)
Requires-Dist: scipy (>=1.15.3,<2.0.0)
Requires-Dist: streamlit (>=1.38.0,<2.0.0)
